bio_embeddings_deepblast-0.1.0.data/scripts/deepblast-evaluate
bio_embeddings_deepblast-0.1.0.data/scripts/deepblast-search
bio_embeddings_deepblast-0.1.0.data/scripts/deepblast-train
bio_embeddings_deepblast-0.1.0.data/scripts/hmm-simulate
deepblast/__init__.py
deepblast/alignment.py
deepblast/constants.py
deepblast/embedding.py
deepblast/language_model.py
deepblast/losses.py
deepblast/nw.py
deepblast/nw_cuda.py
deepblast/ops.py
deepblast/score.py
deepblast/sim.py
deepblast/trainer.py
deepblast/utils.py
deepblast/dataset/__init__.py
deepblast/dataset/alphabet.py
deepblast/dataset/dataset.py
deepblast/dataset/parse_fatcat.py
deepblast/dataset/parse_mali.py
deepblast/dataset/parse_tm_align.py
deepblast/dataset/tm_align.py
deepblast/dataset/utils.py
deepblast/pretrained_models/lstm2x.pt
bio_embeddings_deepblast-0.1.0.dist-info/COPYING.txt
bio_embeddings_deepblast-0.1.0.dist-info/METADATA
bio_embeddings_deepblast-0.1.0.dist-info/WHEEL
bio_embeddings_deepblast-0.1.0.dist-info/top_level.txt
bio_embeddings_deepblast-0.1.0.dist-info/RECORD
