Metadata-Version: 2.1
Name: bio-embeddings-deepblast
Version: 0.1.0
Summary: Deep Sequence Alignments.
Home-page: UNKNOWN
Author-email: jamietmorton@gmail.com
Maintainer-email: jamietmorton@gmail.com
License: BSD-3-Clause
Platform: UNKNOWN
Classifier: Development Status :: 3 - Alpha
Classifier: License :: OSI Approved :: BSD License
Classifier: Topic :: Software Development :: Libraries
Classifier: Topic :: Scientific/Engineering
Classifier: Topic :: Scientific/Engineering :: Bio-Informatics
Classifier: Programming Language :: Python :: 3
Classifier: Programming Language :: Python :: 3 :: Only
Classifier: Programming Language :: Python :: 3.4
Classifier: Programming Language :: Python :: 3.5
Classifier: Programming Language :: Python :: 3.6
Classifier: Programming Language :: Python :: 3.7
Classifier: Operating System :: Unix
Classifier: Operating System :: POSIX
Classifier: Operating System :: MacOS :: MacOS X
Requires-Dist: numpy
Requires-Dist: scipy
Requires-Dist: pandas
Requires-Dist: torch (>=1.4)
Requires-Dist: scikit-learn
Requires-Dist: numba
Requires-Dist: pytorch-lightning (>=0.8.1)
Requires-Dist: matplotlib
Requires-Dist: pillow
